whenact/__init__.py
whenact/context.py
whenact/decision.py
whenact/decisionflow.py
whenact/history.py
whenact/register.py
whenact/types.py
whenact/block/__init__.py
whenact/block/act_decorator.py
whenact/block/when_decorator.py
whenact-0.0.6.dist-info/LICENSE
whenact-0.0.6.dist-info/METADATA
whenact-0.0.6.dist-info/WHEEL
whenact-0.0.6.dist-info/top_level.txt
whenact-0.0.6.dist-info/RECORD
